{
    "office_one": {
        "number": "1.",
        "office_name": "Centro Aurora",
        "location": "https://www.google.com/maps/embed?pb=!1m18!1m12!1m3!1d3596.519951476214!2d13.430572912198352!3d43.2839971761106!2m3!1f0!2f0!3f0!3m2!1i1024!2i768!4f13.1!3m3!1m2!1s0x132df34194d6b717%3A0xf3deb7d0b2fe48e3!2sCentro%20Medico%20Aurora!5e1!3m2!1sit!2sit!4v1729632489245!5m2!1sit!2sit",
        "address": "Via Roma, 408, Macerata",
        "opening":[
            {
                "day": "Martedì: ",
                "time": "15:00 - 20:00"
            },
            {
                "day": "Mercoledì: ",
                "time": "09:00 - 13:00"
            },
            {
                "day": "Venerdì: ",
                "time": "15:00 - 20:00"
            }
        ]
    },
    "office_two": {
        "number": "2.",
        "office_name": "Fiosiomed",
        "location": "https://www.google.com/maps/embed?pb=!1m18!1m12!1m3!1d3597.9617075330343!2d13.429144612197343!3d43.25960447767737!2m3!1f0!2f0!3f0!3m2!1i1024!2i768!4f13.1!3m3!1m2!1s0x132df3fd62973c8b%3A0x4ab003a52777a9e6!2sFisiomed%20-%20Polo%20Diagnostico!5e1!3m2!1sit!2sit!4v1729632802336!5m2!1sit!2sit",
        "address": "Via Giovanni XXIII, Sforxacosta",
        "opening":[
            {
                "day": "Giovedì: ",
                "time": "15:00 - 20:00"
            }
        ]
    }
}
